BasicTools/NumpyDefs.py
BasicTools/__init__.py
BasicTools/__main__.py
BasicTools/Actions/OpenInParaView.py
BasicTools/Actions/__init__.py
BasicTools/Bridges/CGNSBridge.py
BasicTools/Bridges/MeshIOBridge.py
BasicTools/Bridges/PyVistaBridge.py
BasicTools/Bridges/__init__.py
BasicTools/Bridges/gmshBridge.py
BasicTools/Bridges/vtkBridge.py
BasicTools/Containers/ConstantRectilinearMesh.py
BasicTools/Containers/ConstantRectilinearMeshTools.py
BasicTools/Containers/ElementNames.py
BasicTools/Containers/Filters.py
BasicTools/Containers/FiltersTools.py
BasicTools/Containers/MeshBase.py
BasicTools/Containers/MeshTools.py
BasicTools/Containers/SymExpr.py
BasicTools/Containers/Tags.py
BasicTools/Containers/UnstructuredMesh.py
BasicTools/Containers/UnstructuredMeshCreationTools.py
BasicTools/Containers/UnstructuredMeshFieldOperations.py
BasicTools/Containers/UnstructuredMeshGraphTools.py
BasicTools/Containers/UnstructuredMeshInspectionTools.py
BasicTools/Containers/UnstructuredMeshMappingTools.py
BasicTools/Containers/UnstructuredMeshModificationTools.py
BasicTools/Containers/__init__.py
BasicTools/FE/ConstantRectilinearFea.py
BasicTools/FE/DofNumbering.py
BasicTools/FE/FETools.py
BasicTools/FE/FeaBase.py
BasicTools/FE/Integration.py
BasicTools/FE/IntegrationsRules.py
BasicTools/FE/MaterialHelp.py
BasicTools/FE/ProblemData.py
BasicTools/FE/SymPhysics.py
BasicTools/FE/SymWeakForm.py
BasicTools/FE/UnstructuredFeaSym.py
BasicTools/FE/__init__.py
BasicTools/FE/Fields/FEField.py
BasicTools/FE/Fields/FieldBase.py
BasicTools/FE/Fields/FieldTools.py
BasicTools/FE/Fields/IPField.py
BasicTools/FE/Fields/__init__.py
BasicTools/FE/Integrators/PythonIntegration.py
BasicTools/FE/Integrators/__init__.py
BasicTools/FE/KR/KRBase.py
BasicTools/FE/KR/KRBlock.py
BasicTools/FE/KR/KRConformalTie.py
BasicTools/FE/KR/KRDofs.py
BasicTools/FE/KR/KRFromDistribution.py
BasicTools/FE/KR/KRMasterSlaves.py
BasicTools/FE/KR/KRMortar.py
BasicTools/FE/KR/__init__.py
BasicTools/FE/Numberings/DofNumberingDict.py
BasicToolsFrozen-0.0.2.dist-info/CONTRIBUTING.md
BasicToolsFrozen-0.0.2.dist-info/LICENSE.txt
BasicToolsFrozen-0.0.2.dist-info/METADATA
BasicToolsFrozen-0.0.2.dist-info/WHEEL
BasicToolsFrozen-0.0.2.dist-info/top_level.txt
BasicToolsFrozen-0.0.2.dist-info/RECORD
